[
  {
    "label": "WEDDING",
    "content": [
      {
        "story": "Dulce & Lyndon",
        "image": "/assets/weddings/dulce_lyndon.webp"
      },
      {
        "story": "Larah & Adriel",
        "image": "/assets/weddings/larah_adriel.webp"
      },
      {
        "story": "Irma & Jordan",
        "image": "/assets/weddings/irma_jordan.webp"
      },
      {
        "story": "Kris & JC",
        "image": "/assets/weddings/kris_jc.webp"
      },
      {
        "story": "Emilyn & Carl",
        "image": "/assets/weddings/emilyn_carl.webp"
        
      },
      {
        "story": "Peter & Bianca",
        "image": "/assets/weddings/peter_bianca.webp"
      }
    ]
  },
  {
    "label": "PRENUP",
    "content": [
      {
        "story": "Peter & Bianca",
        "image": "/assets/prenup/peter_bianca.webp"
      },
      {
        "story": "John Jeric & Cristalyn",
        "image": "/assets/prenup/john_jeric_cristalyn.webp"
      },
      {
        "story": "Kevin & Shane",
        "image": "/assets/prenup/kevin_shane.webp"
      },
      {
        "story": "Nicole & Russel",
        "image": "/assets/prenup/nicole_russel.webp"
      },
      {
        "story": "Nicole & Russel",
        "image": "/assets/prenup/rocky_michelle.webp"
      },
      {
        "story": "Nicole & Russel",
        "image": "/assets/prenup/jeffrey_ofelia.webp"
      }
    ]
  },
  {
    "label": "DEBUT",
    "content": [
      {
        "story": "Dulce & Lyndon"
      }
    ]
  },
  {
    "label": "CHRISTENING",
    "content": [
      {
        "story": "Dulce & Lyndon"
      }
    ]
  }
]
